[
	{
		"name": "Voca-Ment",
		"replaces": "Monument",
		"uniqueTo": "Mikurium",
		"cityStrength": 1000000000000000000000000000000000000000000,
		"cityHealth": 100000000000000000000000000000000000000000000,
		"culture": 80000000000000000000000000000000000000000000000000,
		"happiness": 800000000000000000000000000000000000000000000000,
		"faith": 8000000000000000000000000000000000000000000000000,
		"science": 800000000000000000000000000000000000000000000000,
		"cost": 0,
		"hurryCostModifier": 800,
		"maintenance": 0,
	},
	{
		"name": "Mikue-Ductos",
		"replaces": "Aqueduct",
		"uniqueTo": "Mikurium",
		"cityStrength": 10000000000000000000000000000000000000000000000000000,
		"cityHealth": 1000000000000000000000000000000000000000000000000000,
		"cost": 0,
		"hurryCostModifier": 160,
		"science": 8000000000000000000000000000000000000000000000,
		"happiness": 80000000000000000000000000000000000000000000000,
		"uniques": ["1000000000000000000000000000000% of food is carried over after a new citizen is born"],
		"requiredTech": "Engineering"
	}
	{
		"name": "Libri-Ku",
		"replaces": "Library",
		"uniqueTo": "Mikurium",
		"cityStrength": 100000000,
		"cityHealth": 100000000,
		"hurryCostModifier": 25,
		"maintenance": 0,
		"uniques": ["[+30 Science] per [18] population [in this city]"],
		"requiredTech": "Writing"
	}
	{
		"name": "Cir-Hatsu",
		"replaces": "Circus",
		"uniqueTo": "Mikurium",
		"cityStrength": 100000000,
		"cityHealth": 100000000,
		"requiredNearbyImprovedResources": ["Ivory","Horses"],
		"happiness": 6,
		"science": 20,
		"hurryCostModifier": 25,
		"requiredTech": "Trapping"
	}
	{
		"name": "Universi-Ku",
		"replaces": "University",
		"uniqueTo": "Mikurium"
		"cityStrength": 100000000,
		"cityHealth": 100000000,
		"maintenance": 1,
		"hurryCostModifier": 15,
		"percentStatBonus": {"science": 180},
		"specialistSlots": {"Scientist": 180},
		"requiredBuilding": "Library",
		"uniques": ["[+200 Science] from [Jungle] tiles [in this city]"],
		"requiredTech": "Education"
	}
	{
		"name": "Mik-Hat-lla",
		"replaces": "Walls",
		"uniqueTo": "Mikurium"
		"cityStrength": 100000000,
		"cityHealth": 100000000,
		"hurryCostModifier": 18,
		"requiredTech": "Agriculture"
	},
]
